arduino_cli_cmake_wrapper/__init__.py
arduino_cli_cmake_wrapper/__main__.py
arduino_cli_cmake_wrapper/_version.py
arduino_cli_cmake_wrapper/builder.py
arduino_cli_cmake_wrapper/cli.py
arduino_cli_cmake_wrapper/miner.py
arduino_cli_cmake_wrapper/parser.py
arduino_cli_cmake_wrapper/types.py
arduino_cli_cmake_wrapper/util.py
arduino_cli_cmake_wrapper-0.2.0a1.dist-info/AUTHORS.rst
arduino_cli_cmake_wrapper-0.2.0a1.dist-info/LICENSE
arduino_cli_cmake_wrapper-0.2.0a1.dist-info/METADATA
arduino_cli_cmake_wrapper-0.2.0a1.dist-info/WHEEL
arduino_cli_cmake_wrapper-0.2.0a1.dist-info/entry_points.txt
arduino_cli_cmake_wrapper-0.2.0a1.dist-info/top_level.txt
arduino_cli_cmake_wrapper-0.2.0a1.dist-info/RECORD
