Metadata-Version: 2.1
Name: arduino-cli-cmake-wrapper
Version: 0.2.0a1
Summary: A wrapper for arduino CLI allowing it to integrate with a CMakeSystem
Author-email: Sterling Lewis Peet <sterling.peet@gatech.edu>, Michael Starch <Michael.D.Starch@jpl.nasa.gov>, Thomas Boyer-Chammard <Thomas.Boyer.Chammard@jpl.nasa.gov>
License: 
Project-URL: Documentation, https://arduino-cli-cmake-wrapper.readthedocs.io/
Project-URL: Changelog, https://arduino-cli-cmake-wrapper.readthedocs.io/en/latest/changelog.html
Project-URL: Issues, https://github.com/SterlingPeet/arduino-cli-cmake-wrapper/issues
Project-URL: Repository, https://github.com/SterlingPeet/arduino-cli-cmake-wrapper
Keywords: fprime,embedded,nasa,arduino,cmake
Classifier: Development Status :: 5 - Production/Stable
Classifier: Intended Audience :: Developers
Classifier: Operating System :: Unix
Classifier: Operating System :: POSIX
Classifier: Programming Language :: Python
Classifier: Programming Language :: Python :: 3
Classifier: Programming Language :: Python :: 3.8
Classifier: Programming Language :: Python :: 3.9
Classifier: Programming Language :: Python :: 3.10
Classifier: Programming Language :: Python :: 3.11
Classifier: Programming Language :: Python :: 3.12
Classifier: Programming Language :: Python :: Implementation :: CPython
Classifier: Programming Language :: Python :: Implementation :: PyPy
Classifier: License :: OSI Approved :: Apache Software License
Classifier: Topic :: Utilities
Requires-Python: >=3.8
License-File: LICENSE
License-File: AUTHORS.rst
